pikselnetbox
