Metadata-Version: 1.0
Name: pikselnetbox
Version: 0.0.9
Summary: Module to automate Netbox
Home-page: http://gitlab.com/joshrchrds/piksel-netbox
Author: Josh Richards
Author-email: joshua.richards135@gmail.com
License: MIT
Platform: UNKNOWN
